{
  "tags": [
    {
      "title": "JavaScript",
      "slug": "old",
      "amountOfVideos": 235
    },
    {
      "title": "JavaScript",
      "slug": "old",
      "amountOfVideos": 289
    },
    {
      "title": "Angular",
      "slug": "old",
      "amountOfVideos": 61
    },
    {
      "title": "HTML",
      "slug": "old",
      "amountOfVideos": 253
    },
    {
      "title": "Vue",
      "slug": "old",
      "amountOfVideos": 286
    },
    {
      "title": "Algorithms",
      "slug": "old",
      "amountOfVideos": 298
    },
    {
      "title": "React",
      "slug": "old",
      "amountOfVideos": 33
    },
    {
      "title": "HTML",
      "slug": "old",
      "amountOfVideos": 168
    },
    {
      "title": "Algorithms",
      "slug": "old",
      "amountOfVideos": 258
    },
    {
      "title": "CSS",
      "slug": "old",
      "amountOfVideos": 47
    },
    {
      "title": "Angular",
      "slug": "old",
      "amountOfVideos": 26
    },
    {
      "title": "HTML",
      "slug": "old",
      "amountOfVideos": 269
    },
    {
      "title": "HTML",
      "slug": "old",
      "amountOfVideos": 263
    },
    {
      "title": "Vue",
      "slug": "old",
      "amountOfVideos": 267
    },
    {
      "title": "CSS",
      "slug": "old",
      "amountOfVideos": 298
    },
    {
      "title": "JavaScript",
      "slug": "old",
      "amountOfVideos": 157
    },
    {
      "title": "React",
      "slug": "old",
      "amountOfVideos": 237
    },
    {
      "title": "JavaScript",
      "slug": "old",
      "amountOfVideos": 66
    },
    {
      "title": "CSS",
      "slug": "old",
      "amountOfVideos": 142
    },
    {
      "title": "Node.js",
      "slug": "old",
      "amountOfVideos": 263
    },
    {
      "title": "React",
      "slug": "old",
      "amountOfVideos": 192
    },
    {
      "title": "Algorithms",
      "slug": "old",
      "amountOfVideos": 101
    },
    {
      "title": "Python",
      "slug": "old",
      "amountOfVideos": 4
    },
    {
      "title": "Algorithms",
      "slug": "old",
      "amountOfVideos": 22
    },
    {
      "title": "Algorithms",
      "slug": "old",
      "amountOfVideos": 253
    },
    {
      "title": "CSS",
      "slug": "old",
      "amountOfVideos": 128
    },
    {
      "title": "Data Structures",
      "slug": "old",
      "amountOfVideos": 242
    },
    {
      "title": "Python",
      "slug": "old",
      "amountOfVideos": 119
    },
    {
      "title": "CSS",
      "slug": "old",
      "amountOfVideos": 294
    },
    {
      "title": "Data Structures",
      "slug": "old",
      "amountOfVideos": 186
    },
    {
      "title": "Python",
      "slug": "old",
      "amountOfVideos": 3
    },
    {
      "title": "Data Structures",
      "slug": "old",
      "amountOfVideos": 254
    },
    {
      "title": "Angular",
      "slug": "old",
      "amountOfVideos": 92
    },
    {
      "title": "Python",
      "slug": "old",
      "amountOfVideos": 39
    },
    {
      "title": "HTML",
      "slug": "old",
      "amountOfVideos": 44
    },
    {
      "title": "Node.js",
      "slug": "old",
      "amountOfVideos": 125
    },
    {
      "title": "Vue",
      "slug": "old",
      "amountOfVideos": 92
    },
    {
      "title": "CSS",
      "slug": "old",
      "amountOfVideos": 69
    },
    {
      "title": "JavaScript",
      "slug": "old",
      "amountOfVideos": 287
    },
    {
      "title": "JavaScript",
      "slug": "old",
      "amountOfVideos": 268
    },
    {
      "title": "Data Structures",
      "slug": "old",
      "amountOfVideos": 211
    },
    {
      "title": "React",
      "slug": "old",
      "amountOfVideos": 155
    },
    {
      "title": "CSS",
      "slug": "old",
      "amountOfVideos": 223
    },
    {
      "title": "HTML",
      "slug": "old",
      "amountOfVideos": 132
    },
    {
      "title": "JavaScript",
      "slug": "old",
      "amountOfVideos": 31
    },
    {
      "title": "Data Structures",
      "slug": "old",
      "amountOfVideos": 244
    },
    {
      "title": "Vue",
      "slug": "old",
      "amountOfVideos": 289
    },
    {
      "title": "JavaScript",
      "slug": "old",
      "amountOfVideos": 149
    },
    {
      "title": "Angular",
      "slug": "old",
      "amountOfVideos": 72
    },
    {
      "title": "Angular",
      "slug": "old",
      "amountOfVideos": 104
    },
    {
      "title": "Angular",
      "slug": "old",
      "amountOfVideos": 152
    },
    {
      "title": "Data Structures",
      "slug": "old",
      "amountOfVideos": 289
    },
    {
      "title": "Data Structures",
      "slug": "old",
      "amountOfVideos": 117
    },
    {
      "title": "Node.js",
      "slug": "old",
      "amountOfVideos": 300
    },
    {
      "title": "Node.js",
      "slug": "old",
      "amountOfVideos": 6
    },
    {
      "title": "CSS",
      "slug": "old",
      "amountOfVideos": 233
    },
    {
      "title": "Data Structures",
      "slug": "old",
      "amountOfVideos": 216
    },
    {
      "title": "Vue",
      "slug": "old",
      "amountOfVideos": 142
    },
    {
      "title": "Data Structures",
      "slug": "old",
      "amountOfVideos": 203
    },
    {
      "title": "Vue",
      "slug": "old",
      "amountOfVideos": 219
    },
    {
      "title": "Angular",
      "slug": "old",
      "amountOfVideos": 65
    },
    {
      "title": "Angular",
      "slug": "old",
      "amountOfVideos": 128
    },
    {
      "title": "React",
      "slug": "old",
      "amountOfVideos": 14
    },
    {
      "title": "Algorithms",
      "slug": "old",
      "amountOfVideos": 254
    },
    {
      "title": "Node.js",
      "slug": "old",
      "amountOfVideos": 148
    },
    {
      "title": "Data Structures",
      "slug": "old",
      "amountOfVideos": 10
    },
    {
      "title": "Node.js",
      "slug": "old",
      "amountOfVideos": 294
    },
    {
      "title": "HTML",
      "slug": "old",
      "amountOfVideos": 98
    },
    {
      "title": "Angular",
      "slug": "old",
      "amountOfVideos": 89
    },
    {
      "title": "CSS",
      "slug": "old",
      "amountOfVideos": 1
    },
    {
      "title": "Data Structures",
      "slug": "old",
      "amountOfVideos": 13
    },
    {
      "title": "JavaScript",
      "slug": "old",
      "amountOfVideos": 144
    },
    {
      "title": "HTML",
      "slug": "old",
      "amountOfVideos": 58
    },
    {
      "title": "Node.js",
      "slug": "old",
      "amountOfVideos": 181
    },
    {
      "title": "HTML",
      "slug": "old",
      "amountOfVideos": 25
    },
    {
      "title": "CSS",
      "slug": "old",
      "amountOfVideos": 45
    },
    {
      "title": "Node.js",
      "slug": "old",
      "amountOfVideos": 221
    },
    {
      "title": "HTML",
      "slug": "old",
      "amountOfVideos": 48
    },
    {
      "title": "CSS",
      "slug": "old",
      "amountOfVideos": 201
    },
    {
      "title": "Vue",
      "slug": "old",
      "amountOfVideos": 159
    },
    {
      "title": "JavaScript",
      "slug": "old",
      "amountOfVideos": 201
    },
    {
      "title": "Angular",
      "slug": "old",
      "amountOfVideos": 45
    },
    {
      "title": "React",
      "slug": "old",
      "amountOfVideos": 125
    },
    {
      "title": "React",
      "slug": "old",
      "amountOfVideos": 132
    },
    {
      "title": "Python",
      "slug": "old",
      "amountOfVideos": 4
    },
    {
      "title": "Angular",
      "slug": "old",
      "amountOfVideos": 63
    },
    {
      "title": "React",
      "slug": "old",
      "amountOfVideos": 85
    },
    {
      "title": "HTML",
      "slug": "old",
      "amountOfVideos": 271
    },
    {
      "title": "JavaScript",
      "slug": "old",
      "amountOfVideos": 111
    },
    {
      "title": "HTML",
      "slug": "old",
      "amountOfVideos": 8
    },
    {
      "title": "Vue",
      "slug": "old",
      "amountOfVideos": 176
    },
    {
      "title": "React",
      "slug": "old",
      "amountOfVideos": 92
    },
    {
      "title": "JavaScript",
      "slug": "old",
      "amountOfVideos": 95
    },
    {
      "title": "Python",
      "slug": "old",
      "amountOfVideos": 100
    },
    {
      "title": "Vue",
      "slug": "old",
      "amountOfVideos": 284
    },
    {
      "title": "Algorithms",
      "slug": "old",
      "amountOfVideos": 286
    },
    {
      "title": "CSS",
      "slug": "old",
      "amountOfVideos": 115
    },
    {
      "title": "Angular",
      "slug": "old",
      "amountOfVideos": 16
    },
    {
      "title": "Node.js",
      "slug": "old",
      "amountOfVideos": 172
    },
    {
      "title": "HTML",
      "slug": "old",
      "amountOfVideos": 176
    },
    {
      "title": "JavaScript",
      "slug": "old",
      "amountOfVideos": 235
    },
    {
      "title": "JavaScript",
      "slug": "old",
      "amountOfVideos": 289
    },
    {
      "title": "Angular",
      "slug": "old",
      "amountOfVideos": 61
    },
    {
      "title": "HTML",
      "slug": "old",
      "amountOfVideos": 253
    },
    {
      "title": "Vue",
      "slug": "old",
      "amountOfVideos": 286
    },
    {
      "title": "Algorithms",
      "slug": "old",
      "amountOfVideos": 298
    },
    {
      "title": "React",
      "slug": "old",
      "amountOfVideos": 33
    },
    {
      "title": "HTML",
      "slug": "old",
      "amountOfVideos": 168
    },
    {
      "title": "Algorithms",
      "slug": "old",
      "amountOfVideos": 258
    },
    {
      "title": "CSS",
      "slug": "old",
      "amountOfVideos": 47
    },
    {
      "title": "Angular",
      "slug": "old",
      "amountOfVideos": 26
    },
    {
      "title": "HTML",
      "slug": "old",
      "amountOfVideos": 269
    },
    {
      "title": "HTML",
      "slug": "old",
      "amountOfVideos": 263
    },
    {
      "title": "Vue",
      "slug": "old",
      "amountOfVideos": 267
    },
    {
      "title": "CSS",
      "slug": "old",
      "amountOfVideos": 298
    },
    {
      "title": "JavaScript",
      "slug": "old",
      "amountOfVideos": 157
    },
    {
      "title": "React",
      "slug": "old",
      "amountOfVideos": 237
    },
    {
      "title": "JavaScript",
      "slug": "old",
      "amountOfVideos": 66
    },
    {
      "title": "CSS",
      "slug": "old",
      "amountOfVideos": 142
    },
    {
      "title": "Node.js",
      "slug": "old",
      "amountOfVideos": 263
    },
    {
      "title": "React",
      "slug": "old",
      "amountOfVideos": 192
    },
    {
      "title": "Algorithms",
      "slug": "old",
      "amountOfVideos": 101
    },
    {
      "title": "Python",
      "slug": "old",
      "amountOfVideos": 4
    },
    {
      "title": "Algorithms",
      "slug": "old",
      "amountOfVideos": 22
    },
    {
      "title": "Algorithms",
      "slug": "old",
      "amountOfVideos": 253
    },
    {
      "title": "CSS",
      "slug": "old",
      "amountOfVideos": 128
    },
    {
      "title": "Data Structures",
      "slug": "old",
      "amountOfVideos": 242
    },
    {
      "title": "Python",
      "slug": "old",
      "amountOfVideos": 119
    },
    {
      "title": "CSS",
      "slug": "old",
      "amountOfVideos": 294
    },
    {
      "title": "Data Structures",
      "slug": "old",
      "amountOfVideos": 186
    },
    {
      "title": "Python",
      "slug": "old",
      "amountOfVideos": 3
    },
    {
      "title": "Data Structures",
      "slug": "old",
      "amountOfVideos": 254
    },
    {
      "title": "Angular",
      "slug": "old",
      "amountOfVideos": 92
    },
    {
      "title": "Python",
      "slug": "old",
      "amountOfVideos": 39
    },
    {
      "title": "HTML",
      "slug": "old",
      "amountOfVideos": 44
    },
    {
      "title": "Node.js",
      "slug": "old",
      "amountOfVideos": 125
    },
    {
      "title": "Vue",
      "slug": "old",
      "amountOfVideos": 92
    },
    {
      "title": "CSS",
      "slug": "old",
      "amountOfVideos": 69
    },
    {
      "title": "JavaScript",
      "slug": "old",
      "amountOfVideos": 287
    },
    {
      "title": "JavaScript",
      "slug": "old",
      "amountOfVideos": 268
    },
    {
      "title": "Data Structures",
      "slug": "old",
      "amountOfVideos": 211
    },
    {
      "title": "React",
      "slug": "old",
      "amountOfVideos": 155
    },
    {
      "title": "CSS",
      "slug": "old",
      "amountOfVideos": 223
    },
    {
      "title": "HTML",
      "slug": "old",
      "amountOfVideos": 132
    },
    {
      "title": "JavaScript",
      "slug": "old",
      "amountOfVideos": 31
    },
    {
      "title": "Data Structures",
      "slug": "old",
      "amountOfVideos": 244
    },
    {
      "title": "Vue",
      "slug": "old",
      "amountOfVideos": 289
    },
    {
      "title": "JavaScript",
      "slug": "old",
      "amountOfVideos": 149
    },
    {
      "title": "Angular",
      "slug": "old",
      "amountOfVideos": 72
    },
    {
      "title": "Angular",
      "slug": "old",
      "amountOfVideos": 104
    },
    {
      "title": "Angular",
      "slug": "old",
      "amountOfVideos": 152
    },
    {
      "title": "Data Structures",
      "slug": "old",
      "amountOfVideos": 289
    },
    {
      "title": "Data Structures",
      "slug": "old",
      "amountOfVideos": 117
    },
    {
      "title": "Node.js",
      "slug": "old",
      "amountOfVideos": 300
    },
    {
      "title": "Node.js",
      "slug": "old",
      "amountOfVideos": 6
    },
    {
      "title": "CSS",
      "slug": "old",
      "amountOfVideos": 233
    },
    {
      "title": "Data Structures",
      "slug": "old",
      "amountOfVideos": 216
    },
    {
      "title": "Vue",
      "slug": "old",
      "amountOfVideos": 142
    },
    {
      "title": "Data Structures",
      "slug": "old",
      "amountOfVideos": 203
    },
    {
      "title": "Vue",
      "slug": "old",
      "amountOfVideos": 219
    },
    {
      "title": "Angular",
      "slug": "old",
      "amountOfVideos": 65
    },
    {
      "title": "Angular",
      "slug": "old",
      "amountOfVideos": 128
    },
    {
      "title": "React",
      "slug": "old",
      "amountOfVideos": 14
    },
    {
      "title": "Algorithms",
      "slug": "old",
      "amountOfVideos": 254
    },
    {
      "title": "Node.js",
      "slug": "old",
      "amountOfVideos": 148
    },
    {
      "title": "Data Structures",
      "slug": "old",
      "amountOfVideos": 10
    },
    {
      "title": "Node.js",
      "slug": "old",
      "amountOfVideos": 294
    },
    {
      "title": "HTML",
      "slug": "old",
      "amountOfVideos": 98
    },
    {
      "title": "Angular",
      "slug": "old",
      "amountOfVideos": 89
    },
    {
      "title": "CSS",
      "slug": "old",
      "amountOfVideos": 1
    },
    {
      "title": "Data Structures",
      "slug": "old",
      "amountOfVideos": 13
    },
    {
      "title": "JavaScript",
      "slug": "old",
      "amountOfVideos": 144
    },
    {
      "title": "HTML",
      "slug": "old",
      "amountOfVideos": 58
    },
    {
      "title": "Node.js",
      "slug": "old",
      "amountOfVideos": 181
    },
    {
      "title": "HTML",
      "slug": "old",
      "amountOfVideos": 25
    },
    {
      "title": "CSS",
      "slug": "old",
      "amountOfVideos": 45
    },
    {
      "title": "Node.js",
      "slug": "old",
      "amountOfVideos": 221
    },
    {
      "title": "HTML",
      "slug": "old",
      "amountOfVideos": 48
    },
    {
      "title": "CSS",
      "slug": "old",
      "amountOfVideos": 201
    },
    {
      "title": "Vue",
      "slug": "old",
      "amountOfVideos": 159
    },
    {
      "title": "JavaScript",
      "slug": "old",
      "amountOfVideos": 201
    },
    {
      "title": "Angular",
      "slug": "old",
      "amountOfVideos": 45
    },
    {
      "title": "React",
      "slug": "old",
      "amountOfVideos": 125
    },
    {
      "title": "React",
      "slug": "old",
      "amountOfVideos": 132
    },
    {
      "title": "Python",
      "slug": "old",
      "amountOfVideos": 4
    },
    {
      "title": "Angular",
      "slug": "old",
      "amountOfVideos": 63
    },
    {
      "title": "React",
      "slug": "old",
      "amountOfVideos": 85
    },
    {
      "title": "HTML",
      "slug": "old",
      "amountOfVideos": 271
    },
    {
      "title": "JavaScript",
      "slug": "old",
      "amountOfVideos": 111
    },
    {
      "title": "HTML",
      "slug": "old",
      "amountOfVideos": 8
    },
    {
      "title": "Vue",
      "slug": "old",
      "amountOfVideos": 176
    },
    {
      "title": "React",
      "slug": "old",
      "amountOfVideos": 92
    },
    {
      "title": "JavaScript",
      "slug": "old",
      "amountOfVideos": 95
    },
    {
      "title": "Python",
      "slug": "old",
      "amountOfVideos": 100
    },
    {
      "title": "Vue",
      "slug": "old",
      "amountOfVideos": 284
    },
    {
      "title": "Algorithms",
      "slug": "old",
      "amountOfVideos": 286
    },
    {
      "title": "CSS",
      "slug": "old",
      "amountOfVideos": 115
    },
    {
      "title": "Angular",
      "slug": "old",
      "amountOfVideos": 16
    },
    {
      "title": "Node.js",
      "slug": "old",
      "amountOfVideos": 172
    },
    {
      "title": "HTML",
      "slug": "old",
      "amountOfVideos": 176
    },
    {
      "id": "940d",
      "title": "agora vai slig",
      "slug": "agora-vai-slig",
      "amountOfVideos": 0
    },
    {
      "id": "0c07",
      "title": "agora vai slig",
      "slug": "agora-vai-slig",
      "amountOfVideos": 0
    },
    {
      "id": "bcdd",
      "title": "teste",
      "slug": "teste",
      "amountOfVideos": 0
    }
  ]
}